opengine2/__init__.py
opengine2/__main__.py
opengine2/cfg.py
opengine2/grkcyr.opengine2.hocon
opengine2/gui.py
opengine2/ipa.opengine2.toml
opengine2/kbds.py
opengine2-2.0.1.dist-info/licenses/LICENSE
opengine2-2.0.1.dist-info/METADATA
opengine2-2.0.1.dist-info/WHEEL
opengine2-2.0.1.dist-info/entry_points.txt
opengine2-2.0.1.dist-info/top_level.txt
opengine2-2.0.1.dist-info/RECORD
