Metadata-Version: 2.4
Name: opengine2
Version: 2.0.1
Summary: A text box that allows easier input of many characters in a structured way.
Requires-Python: >=3.12
License-File: LICENSE
Requires-Dist: inline>=0.0.1
Requires-Dist: pyhocon>=0.3.61
Requires-Dist: pyside6>=6.9.1
Requires-Dist: pyxdg>=0.28
Dynamic: license-file
